logtale/__init__.py
logtale/filter.py
logtale/formatter.py
logtale/logtale.py
logtale-0.0.11.dist-info/LICENSE
logtale-0.0.11.dist-info/METADATA
logtale-0.0.11.dist-info/WHEEL
logtale-0.0.11.dist-info/top_level.txt
logtale-0.0.11.dist-info/RECORD
