Metadata-Version: 2.1
Name: logtale
Version: 0.0.11
Summary: A simple, easy to use python logging framework that builds on top of the built-in logger module
Author: Jason Jerome
Project-URL: Homepage, https://github.com/DuckBoss/logtale
Project-URL: Documentation, https://github.com/DuckBoss/logtale
Project-URL: Repository, https://github.com/DuckBoss/logtale.git
Project-URL: Issues, https://github.com/DuckBoss/logtale/issues
Project-URL: Changelog, https://github.com/DuckBoss/logtale/blob/master/CHANGELOG.md
Keywords: python,logging,log,logger
Classifier: License :: OSI Approved :: GNU General Public License v3 (GPLv3)
Classifier: Programming Language :: Python :: 3
Classifier: Programming Language :: Python :: 3.6
Classifier: Programming Language :: Python :: 3.7
Classifier: Programming Language :: Python :: 3.8
Classifier: Programming Language :: Python :: 3.9
Classifier: Programming Language :: Python :: 3.10
Classifier: Programming Language :: Python :: 3.11
Classifier: Programming Language :: Python :: 3.12
Classifier: Operating System :: OS Independent
Classifier: Topic :: System :: Logging
Requires-Python: >=3.8
License-File: LICENSE
Requires-Dist: python-dotenv
Requires-Dist: toml
